indoxRag/__init__.py
indoxRag/indoxRag.py
indoxRag/utils.py
indoxRag/core/__init__.py
indoxRag/core/base_llm.py
indoxRag/core/document_object.py
indoxRag/core/embeddings.py
indoxRag/core/vectorstore.py
indoxRag/data_connectors/__init__.py
indoxRag/data_connectors/arxiv.py
indoxRag/data_connectors/discord.py
indoxRag/data_connectors/github.py
indoxRag/data_connectors/guten.py
indoxRag/data_connectors/twitter.py
indoxRag/data_connectors/wikipedia.py
indoxRag/data_connectors/youtube.py
indoxRag/data_connectors/google/__init__.py
indoxRag/data_connectors/google/googleChat.py
indoxRag/data_connectors/google/googleDoc.py
indoxRag/data_connectors/google/googleDrive.py
indoxRag/data_connectors/google/goolgeSheet.py
indoxRag/data_connectors/google/maps_search.py
indoxRag/data_connectors/utils/__init__.py
indoxRag/data_connectors/utils/document.py
indoxRag/data_loader_splitter/__init__.py
indoxRag/data_loader_splitter/ClusteredSplit/Clustering.py
indoxRag/data_loader_splitter/ClusteredSplit/Embed.py
indoxRag/data_loader_splitter/ClusteredSplit/EmbedClusterSummarize.py
indoxRag/data_loader_splitter/ClusteredSplit/__init__.py
indoxRag/data_loader_splitter/ClusteredSplit/cs_utils.py
indoxRag/data_loader_splitter/ClusteredSplit/split.py
indoxRag/data_loader_splitter/SimpleLoadAndSplit/__init__.py
indoxRag/data_loader_splitter/SimpleLoadAndSplit/loader.py
indoxRag/data_loader_splitter/SimpleLoadAndSplit/split.py
indoxRag/data_loader_splitter/UnstructuredLoadAndSplit/__init__.py
indoxRag/data_loader_splitter/UnstructuredLoadAndSplit/split.py
indoxRag/data_loader_splitter/utils/__init__.py
indoxRag/data_loader_splitter/utils/clean.py
indoxRag/data_loader_splitter/utils/unstructured_utills.py
indoxRag/data_loaders/__init__.py
indoxRag/data_loaders/bs4.py
indoxRag/data_loaders/csv.py
indoxRag/data_loaders/docling.py
indoxRag/data_loaders/docx.py
indoxRag/data_loaders/excel.py
indoxRag/data_loaders/html.py
indoxRag/data_loaders/joblib.py
indoxRag/data_loaders/json.py
indoxRag-0.1.1.dist-info/LICENSE
indoxRag-0.1.1.dist-info/METADATA
indoxRag-0.1.1.dist-info/WHEEL
indoxRag-0.1.1.dist-info/top_level.txt
indoxRag-0.1.1.dist-info/RECORD
