Metadata-Version: 2.1
Name: indoxRag
Version: 0.1.1
Summary: Indox Retrieval Augmentation
Home-page: https://github.com/osllmai/inDox/libs/indoxRag
Author: osllm.ai
Author-email: ashkan@nematifamilyfundation.onmicrosoft.com
License: AGPL-3.0
Keywords: RAG,LLM,retrieval-augmented generation,machine learning,natural language processing,NLP,AI,deep learning,language models
Classifier: Development Status :: 3 - Alpha
Classifier: Intended Audience :: Developers
Classifier: Topic :: Software Development :: Build Tools
Classifier: License :: OSI Approved :: GNU Affero General Public License v3 or later (AGPLv3+)
Classifier: Programming Language :: Python :: 3.9
Classifier: Programming Language :: Python :: 3.10
Classifier: Programming Language :: Python :: 3.11
Classifier: Programming Language :: Python :: 3.12
Requires-Python: >=3.9
License-File: LICENSE
Requires-Dist: latex2markdown
Requires-Dist: loguru
Requires-Dist: numpy
Requires-Dist: pandas
Requires-Dist: protobuf
Requires-Dist: pydantic
Requires-Dist: PyPDF2
Requires-Dist: python-dotenv
Requires-Dist: Requests
Requires-Dist: setuptools
Requires-Dist: tenacity
Requires-Dist: tiktoken
Requires-Dist: tokenizers
Requires-Dist: umap-learn
Requires-Dist: unstructured
Requires-Dist: nltk
Requires-Dist: pillow-heif
